{"dependencies":[{"name":"D:\\parcel-test\\IFEMvvm2.1\\package.json","includedInParent":true,"mtime":1524894956033},{"name":"san","loc":{"line":3,"column":7}}],"generated":{"js":"'use strict';\n\nvar _san = require('san');\n\nvar _san2 = _interopRequireDefault(_san);\n\nfunction _interopRequireDefault(obj) { return obj && obj.__esModule ? obj : { default: obj }; }\n\nvar MyApp = _san2.default.defineComponent({\n  template: '\\\r\n        <div class=\"container\">\\\r\n            <ul class=\"u_input\">\\\r\n                <li><input type=\"text\" placeholder=\"姓名\" value=\"{= name =}\" on-input=\"setName\"/></li>\\\r\n                <li><input type=\"number\" placeholder=\"年龄\" value=\"{= age =}\" on-input=\"setAge\"/></li>\\\r\n                <li><input type=\"text\" placeholder=\"简介\" value=\"{= pro =}\" on-input=\"setPro\"/></li>\\\r\n            </ul>\\\r\n            <button type=\"button\" on-click=\"rm\">移除信息</button>\\\r\n            <ul class=\"u_span\">\\\r\n                <li>姓名:<span>{{name}}</span></li>\\\r\n                <li>年龄:<span>{{age}}</span></li>\\\r\n                <li>简介:<span>{{pro}}</span></li>\\\r\n            </ul>\\\r\n        </div>\\\r\n        ',\n  initData: function initData() {\n    return {\n      person: {\n        name: undefined,\n        age: undefined,\n        pro: undefined\n      }\n    };\n  },\n  person: _san.DataTypes.shape({\n    name: _san.DataTypes.string,\n    age: _san.DataTypes.number,\n    pro: _san.DataTypes.string\n  }),\n  rm: function rm() {\n    this.data.set('name', '');\n    this.data.set('age', '');\n    this.data.set('pro', '');\n  },\n  setName: function setName() {\n    this.data.set(\"person.name\", this.data.get(\"name\"));\n  },\n  setAge: function setAge() {\n    this.data.set(\"person.age\", isNaN(parseInt(this.data.get(\"age\"))) ? undefined : parseInt(this.data.get(\"age\")));\n  },\n  setPro: function setPro() {\n    this.data.set(\"person.pro\", this.data.get(\"pro\"));\n  }\n});\n\nvar myApp = new MyApp();\nmyApp.attach(document.body);","map":{"mappings":[{"generated":{"line":3,"column":0},"source":"src\\main.js","original":{"line":1,"column":0}},{"generated":{"line":9,"column":0},"source":"src\\main.js","original":{"line":5,"column":0}},{"name":"MyApp","generated":{"line":9,"column":4},"source":"src\\main.js","original":{"line":5,"column":6}},{"name":"san","generated":{"line":9,"column":12},"source":"src\\main.js","original":{"line":5,"column":14}},{"name":"defineComponent","generated":{"line":9,"column":26},"source":"src\\main.js","original":{"line":5,"column":18}},{"generated":{"line":9,"column":41},"source":"src\\main.js","original":{"line":5,"column":14}},{"generated":{"line":9,"column":42},"source":"src\\main.js","original":{"line":5,"column":34}},{"name":"template","generated":{"line":10,"column":0},"source":"src\\main.js","original":{"line":6,"column":2}},{"generated":{"line":10,"column":12},"source":"src\\main.js","original":{"line":6,"column":12}},{"generated":{"line":24,"column":9},"source":"src\\main.js","original":{"line":5,"column":34}},{"name":"initData","generated":{"line":25,"column":0},"source":"src\\main.js","original":{"line":21,"column":2}},{"generated":{"line":25,"column":12},"source":"src\\main.js","original":{"line":21,"column":12}},{"generated":{"line":25,"column":32},"source":"src\\main.js","original":{"line":21,"column":24}},{"generated":{"line":26,"column":0},"source":"src\\main.js","original":{"line":22,"column":4}},{"generated":{"line":26,"column":11},"source":"src\\main.js","original":{"line":22,"column":11}},{"name":"person","generated":{"line":27,"column":0},"source":"src\\main.js","original":{"line":23,"column":6}},{"generated":{"line":27,"column":14},"source":"src\\main.js","original":{"line":23,"column":14}},{"name":"name","generated":{"line":28,"column":0},"source":"src\\main.js","original":{"line":24,"column":8}},{"name":"undefined","generated":{"line":28,"column":14},"source":"src\\main.js","original":{"line":24,"column":14}},{"generated":{"line":28,"column":23},"source":"src\\main.js","original":{"line":23,"column":14}},{"name":"age","generated":{"line":29,"column":0},"source":"src\\main.js","original":{"line":25,"column":8}},{"name":"undefined","generated":{"line":29,"column":13},"source":"src\\main.js","original":{"line":25,"column":13}},{"generated":{"line":29,"column":22},"source":"src\\main.js","original":{"line":23,"column":14}},{"name":"pro","generated":{"line":30,"column":0},"source":"src\\main.js","original":{"line":26,"column":8}},{"name":"undefined","generated":{"line":30,"column":13},"source":"src\\main.js","original":{"line":26,"column":13}},{"generated":{"line":31,"column":0},"source":"src\\main.js","original":{"line":23,"column":14}},{"generated":{"line":32,"column":0},"source":"src\\main.js","original":{"line":22,"column":11}},{"generated":{"line":32,"column":5},"source":"src\\main.js","original":{"line":22,"column":4}},{"generated":{"line":33,"column":0},"source":"src\\main.js","original":{"line":29,"column":3}},{"generated":{"line":33,"column":3},"source":"src\\main.js","original":{"line":5,"column":34}},{"name":"person","generated":{"line":34,"column":0},"source":"src\\main.js","original":{"line":30,"column":2}},{"name":"DataTypes","generated":{"line":34,"column":10},"source":"src\\main.js","original":{"line":30,"column":10}},{"name":"shape","generated":{"line":34,"column":25},"source":"src\\main.js","original":{"line":30,"column":20}},{"generated":{"line":34,"column":30},"source":"src\\main.js","original":{"line":30,"column":10}},{"generated":{"line":34,"column":31},"source":"src\\main.js","original":{"line":30,"column":26}},{"name":"name","generated":{"line":35,"column":0},"source":"src\\main.js","original":{"line":31,"column":4}},{"name":"DataTypes","generated":{"line":35,"column":10},"source":"src\\main.js","original":{"line":31,"column":10}},{"name":"string","generated":{"line":35,"column":25},"source":"src\\main.js","original":{"line":31,"column":20}},{"generated":{"line":35,"column":31},"source":"src\\main.js","original":{"line":30,"column":26}},{"name":"age","generated":{"line":36,"column":0},"source":"src\\main.js","original":{"line":32,"column":4}},{"name":"DataTypes","generated":{"line":36,"column":9},"source":"src\\main.js","original":{"line":32,"column":9}},{"name":"number","generated":{"line":36,"column":24},"source":"src\\main.js","original":{"line":32,"column":19}},{"generated":{"line":36,"column":30},"source":"src\\main.js","original":{"line":30,"column":26}},{"name":"pro","generated":{"line":37,"column":0},"source":"src\\main.js","original":{"line":33,"column":4}},{"name":"DataTypes","generated":{"line":37,"column":9},"source":"src\\main.js","original":{"line":33,"column":9}},{"name":"string","generated":{"line":37,"column":24},"source":"src\\main.js","original":{"line":33,"column":19}},{"generated":{"line":38,"column":0},"source":"src\\main.js","original":{"line":30,"column":26}},{"generated":{"line":38,"column":3},"source":"src\\main.js","original":{"line":30,"column":10}},{"generated":{"line":38,"column":4},"source":"src\\main.js","original":{"line":5,"column":34}},{"name":"rm","generated":{"line":39,"column":0},"source":"src\\main.js","original":{"line":35,"column":2}},{"generated":{"line":39,"column":6},"source":"src\\main.js","original":{"line":35,"column":6}},{"generated":{"line":39,"column":20},"source":"src\\main.js","original":{"line":35,"column":18}},{"generated":{"line":40,"column":0},"source":"src\\main.js","original":{"line":36,"column":4}},{"name":"data","generated":{"line":40,"column":9},"source":"src\\main.js","original":{"line":36,"column":9}},{"generated":{"line":40,"column":13},"source":"src\\main.js","original":{"line":36,"column":4}},{"name":"set","generated":{"line":40,"column":14},"source":"src\\main.js","original":{"line":36,"column":14}},{"generated":{"line":40,"column":17},"source":"src\\main.js","original":{"line":36,"column":4}},{"generated":{"line":40,"column":18},"source":"src\\main.js","original":{"line":36,"column":18}},{"generated":{"line":40,"column":24},"source":"src\\main.js","original":{"line":36,"column":4}},{"generated":{"line":40,"column":26},"source":"src\\main.js","original":{"line":36,"column":26}},{"generated":{"line":40,"column":28},"source":"src\\main.js","original":{"line":36,"column":4}},{"generated":{"line":41,"column":0},"source":"src\\main.js","original":{"line":37,"column":4}},{"name":"data","generated":{"line":41,"column":9},"source":"src\\main.js","original":{"line":37,"column":9}},{"generated":{"line":41,"column":13},"source":"src\\main.js","original":{"line":37,"column":4}},{"name":"set","generated":{"line":41,"column":14},"source":"src\\main.js","original":{"line":37,"column":14}},{"generated":{"line":41,"column":17},"source":"src\\main.js","original":{"line":37,"column":4}},{"generated":{"line":41,"column":18},"source":"src\\main.js","original":{"line":37,"column":18}},{"generated":{"line":41,"column":23},"source":"src\\main.js","original":{"line":37,"column":4}},{"generated":{"line":41,"column":25},"source":"src\\main.js","original":{"line":37,"column":25}},{"generated":{"line":41,"column":27},"source":"src\\main.js","original":{"line":37,"column":4}},{"generated":{"line":42,"column":0},"source":"src\\main.js","original":{"line":38,"column":4}},{"name":"data","generated":{"line":42,"column":9},"source":"src\\main.js","original":{"line":38,"column":9}},{"generated":{"line":42,"column":13},"source":"src\\main.js","original":{"line":38,"column":4}},{"name":"set","generated":{"line":42,"column":14},"source":"src\\main.js","original":{"line":38,"column":14}},{"generated":{"line":42,"column":17},"source":"src\\main.js","original":{"line":38,"column":4}},{"generated":{"line":42,"column":18},"source":"src\\main.js","original":{"line":38,"column":18}},{"generated":{"line":42,"column":23},"source":"src\\main.js","original":{"line":38,"column":4}},{"generated":{"line":42,"column":25},"source":"src\\main.js","original":{"line":38,"column":25}},{"generated":{"line":42,"column":27},"source":"src\\main.js","original":{"line":38,"column":4}},{"generated":{"line":43,"column":0},"source":"src\\main.js","original":{"line":39,"column":3}},{"generated":{"line":43,"column":3},"source":"src\\main.js","original":{"line":5,"column":34}},{"name":"setName","generated":{"line":44,"column":0},"source":"src\\main.js","original":{"line":40,"column":2}},{"generated":{"line":44,"column":11},"source":"src\\main.js","original":{"line":40,"column":11}},{"generated":{"line":44,"column":30},"source":"src\\main.js","original":{"line":40,"column":23}},{"generated":{"line":45,"column":0},"source":"src\\main.js","original":{"line":41,"column":4}},{"name":"data","generated":{"line":45,"column":9},"source":"src\\main.js","original":{"line":41,"column":9}},{"generated":{"line":45,"column":13},"source":"src\\main.js","original":{"line":41,"column":4}},{"name":"set","generated":{"line":45,"column":14},"source":"src\\main.js","original":{"line":41,"column":14}},{"generated":{"line":45,"column":17},"source":"src\\main.js","original":{"line":41,"column":4}},{"generated":{"line":45,"column":18},"source":"src\\main.js","original":{"line":41,"column":18}},{"generated":{"line":45,"column":31},"source":"src\\main.js","original":{"line":41,"column":4}},{"generated":{"line":45,"column":33},"source":"src\\main.js","original":{"line":41,"column":33}},{"name":"data","generated":{"line":45,"column":38},"source":"src\\main.js","original":{"line":41,"column":38}},{"generated":{"line":45,"column":42},"source":"src\\main.js","original":{"line":41,"column":33}},{"name":"get","generated":{"line":45,"column":43},"source":"src\\main.js","original":{"line":41,"column":43}},{"generated":{"line":45,"column":46},"source":"src\\main.js","original":{"line":41,"column":33}},{"generated":{"line":45,"column":47},"source":"src\\main.js","original":{"line":41,"column":47}},{"generated":{"line":45,"column":53},"source":"src\\main.js","original":{"line":41,"column":33}},{"generated":{"line":45,"column":54},"source":"src\\main.js","original":{"line":41,"column":4}},{"generated":{"line":46,"column":0},"source":"src\\main.js","original":{"line":42,"column":3}},{"generated":{"line":46,"column":3},"source":"src\\main.js","original":{"line":5,"column":34}},{"name":"setAge","generated":{"line":47,"column":0},"source":"src\\main.js","original":{"line":43,"column":2}},{"generated":{"line":47,"column":10},"source":"src\\main.js","original":{"line":43,"column":10}},{"generated":{"line":47,"column":28},"source":"src\\main.js","original":{"line":43,"column":22}},{"generated":{"line":48,"column":0},"source":"src\\main.js","original":{"line":44,"column":4}},{"name":"data","generated":{"line":48,"column":9},"source":"src\\main.js","original":{"line":44,"column":9}},{"generated":{"line":48,"column":13},"source":"src\\main.js","original":{"line":44,"column":4}},{"name":"set","generated":{"line":48,"column":14},"source":"src\\main.js","original":{"line":44,"column":14}},{"generated":{"line":48,"column":17},"source":"src\\main.js","original":{"line":44,"column":4}},{"generated":{"line":48,"column":18},"source":"src\\main.js","original":{"line":44,"column":18}},{"generated":{"line":48,"column":30},"source":"src\\main.js","original":{"line":44,"column":4}},{"name":"isNaN","generated":{"line":48,"column":32},"source":"src\\main.js","original":{"line":44,"column":32}},{"name":"parseInt","generated":{"line":48,"column":38},"source":"src\\main.js","original":{"line":44,"column":38}},{"generated":{"line":48,"column":47},"source":"src\\main.js","original":{"line":44,"column":47}},{"name":"data","generated":{"line":48,"column":52},"source":"src\\main.js","original":{"line":44,"column":52}},{"generated":{"line":48,"column":56},"source":"src\\main.js","original":{"line":44,"column":47}},{"name":"get","generated":{"line":48,"column":57},"source":"src\\main.js","original":{"line":44,"column":57}},{"generated":{"line":48,"column":60},"source":"src\\main.js","original":{"line":44,"column":47}},{"generated":{"line":48,"column":61},"source":"src\\main.js","original":{"line":44,"column":61}},{"generated":{"line":48,"column":66},"source":"src\\main.js","original":{"line":44,"column":47}},{"generated":{"line":48,"column":67},"source":"src\\main.js","original":{"line":44,"column":38}},{"generated":{"line":48,"column":68},"source":"src\\main.js","original":{"line":44,"column":32}},{"name":"undefined","generated":{"line":48,"column":72},"source":"src\\main.js","original":{"line":44,"column":72}},{"generated":{"line":48,"column":81},"source":"src\\main.js","original":{"line":44,"column":32}},{"name":"parseInt","generated":{"line":48,"column":84},"source":"src\\main.js","original":{"line":44,"column":84}},{"generated":{"line":48,"column":93},"source":"src\\main.js","original":{"line":44,"column":93}},{"name":"data","generated":{"line":48,"column":98},"source":"src\\main.js","original":{"line":44,"column":98}},{"generated":{"line":48,"column":102},"source":"src\\main.js","original":{"line":44,"column":93}},{"name":"get","generated":{"line":48,"column":103},"source":"src\\main.js","original":{"line":44,"column":103}},{"generated":{"line":48,"column":106},"source":"src\\main.js","original":{"line":44,"column":93}},{"generated":{"line":48,"column":107},"source":"src\\main.js","original":{"line":44,"column":107}},{"generated":{"line":48,"column":112},"source":"src\\main.js","original":{"line":44,"column":93}},{"generated":{"line":48,"column":113},"source":"src\\main.js","original":{"line":44,"column":84}},{"generated":{"line":48,"column":114},"source":"src\\main.js","original":{"line":44,"column":4}},{"generated":{"line":49,"column":0},"source":"src\\main.js","original":{"line":45,"column":3}},{"generated":{"line":49,"column":3},"source":"src\\main.js","original":{"line":5,"column":34}},{"name":"setPro","generated":{"line":50,"column":0},"source":"src\\main.js","original":{"line":46,"column":2}},{"generated":{"line":50,"column":10},"source":"src\\main.js","original":{"line":46,"column":10}},{"generated":{"line":50,"column":28},"source":"src\\main.js","original":{"line":46,"column":22}},{"generated":{"line":51,"column":0},"source":"src\\main.js","original":{"line":47,"column":4}},{"name":"data","generated":{"line":51,"column":9},"source":"src\\main.js","original":{"line":47,"column":9}},{"generated":{"line":51,"column":13},"source":"src\\main.js","original":{"line":47,"column":4}},{"name":"set","generated":{"line":51,"column":14},"source":"src\\main.js","original":{"line":47,"column":14}},{"generated":{"line":51,"column":17},"source":"src\\main.js","original":{"line":47,"column":4}},{"generated":{"line":51,"column":18},"source":"src\\main.js","original":{"line":47,"column":18}},{"generated":{"line":51,"column":30},"source":"src\\main.js","original":{"line":47,"column":4}},{"generated":{"line":51,"column":32},"source":"src\\main.js","original":{"line":47,"column":32}},{"name":"data","generated":{"line":51,"column":37},"source":"src\\main.js","original":{"line":47,"column":37}},{"generated":{"line":51,"column":41},"source":"src\\main.js","original":{"line":47,"column":32}},{"name":"get","generated":{"line":51,"column":42},"source":"src\\main.js","original":{"line":47,"column":42}},{"generated":{"line":51,"column":45},"source":"src\\main.js","original":{"line":47,"column":32}},{"generated":{"line":51,"column":46},"source":"src\\main.js","original":{"line":47,"column":46}},{"generated":{"line":51,"column":51},"source":"src\\main.js","original":{"line":47,"column":32}},{"generated":{"line":51,"column":52},"source":"src\\main.js","original":{"line":47,"column":4}},{"generated":{"line":52,"column":0},"source":"src\\main.js","original":{"line":48,"column":3}},{"generated":{"line":53,"column":0},"source":"src\\main.js","original":{"line":5,"column":34}},{"generated":{"line":53,"column":1},"source":"src\\main.js","original":{"line":5,"column":14}},{"generated":{"line":53,"column":2},"source":"src\\main.js","original":{"line":5,"column":0}},{"generated":{"line":55,"column":0},"source":"src\\main.js","original":{"line":51,"column":0}},{"name":"myApp","generated":{"line":55,"column":4},"source":"src\\main.js","original":{"line":51,"column":6}},{"generated":{"line":55,"column":12},"source":"src\\main.js","original":{"line":51,"column":14}},{"name":"MyApp","generated":{"line":55,"column":16},"source":"src\\main.js","original":{"line":51,"column":18}},{"generated":{"line":55,"column":21},"source":"src\\main.js","original":{"line":51,"column":14}},{"generated":{"line":55,"column":23},"source":"src\\main.js","original":{"line":51,"column":0}},{"name":"myApp","generated":{"line":56,"column":0},"source":"src\\main.js","original":{"line":52,"column":0}},{"name":"attach","generated":{"line":56,"column":6},"source":"src\\main.js","original":{"line":52,"column":6}},{"generated":{"line":56,"column":12},"source":"src\\main.js","original":{"line":52,"column":0}},{"name":"document","generated":{"line":56,"column":13},"source":"src\\main.js","original":{"line":52,"column":13}},{"name":"body","generated":{"line":56,"column":22},"source":"src\\main.js","original":{"line":52,"column":22}},{"generated":{"line":56,"column":26},"source":"src\\main.js","original":{"line":52,"column":0}}],"sources":{"src\\main.js":"import san, {\r\n  DataTypes\r\n} from \"san\"\r\n\r\nconst MyApp = san.defineComponent({\r\n  template: '\\\r\n        <div class=\"container\">\\\r\n            <ul class=\"u_input\">\\\r\n                <li><input type=\"text\" placeholder=\"姓名\" value=\"{= name =}\" on-input=\"setName\"/></li>\\\r\n                <li><input type=\"number\" placeholder=\"年龄\" value=\"{= age =}\" on-input=\"setAge\"/></li>\\\r\n                <li><input type=\"text\" placeholder=\"简介\" value=\"{= pro =}\" on-input=\"setPro\"/></li>\\\r\n            </ul>\\\r\n            <button type=\"button\" on-click=\"rm\">移除信息</button>\\\r\n            <ul class=\"u_span\">\\\r\n                <li>姓名:<span>{{name}}</span></li>\\\r\n                <li>年龄:<span>{{age}}</span></li>\\\r\n                <li>简介:<span>{{pro}}</span></li>\\\r\n            </ul>\\\r\n        </div>\\\r\n        ',\r\n  initData: function () {\r\n    return {\r\n      person: {\r\n        name: undefined,\r\n        age: undefined,\r\n        pro: undefined\r\n      }\r\n    };\r\n  },\r\n  person: DataTypes.shape({\r\n    name: DataTypes.string,\r\n    age: DataTypes.number,\r\n    pro: DataTypes.string\r\n  }),\r\n  rm: function () {\r\n    this.data.set('name', '');\r\n    this.data.set('age', '');\r\n    this.data.set('pro', '');\r\n  },\r\n  setName: function () {\r\n    this.data.set(\"person.name\", this.data.get(\"name\"));\r\n  },\r\n  setAge: function () {\r\n    this.data.set(\"person.age\", isNaN(parseInt(this.data.get(\"age\"))) ? undefined : parseInt(this.data.get(\"age\")));\r\n  },\r\n  setPro: function () {\r\n    this.data.set(\"person.pro\", this.data.get(\"pro\"));\r\n  }\r\n});\r\n\r\nconst myApp = new MyApp();\r\nmyApp.attach(document.body);"},"lineCount":null}},"hash":"75cccf8af793d160b37bb7ebcfa2474e","cacheData":{"env":{}}}